LbPlatformUtils/__init__.py
LbPlatformUtils/_arch_details/__init__.py
LbPlatformUtils/_arch_details/_arm.py
LbPlatformUtils/_arch_details/_intel.py
LbPlatformUtils/architectures.py
LbPlatformUtils/bash-completion/README.txt
LbPlatformUtils/bash-completion/_lb-describe-platform
LbPlatformUtils/bash-completion/_lb-host-binary-tag
LbPlatformUtils/debug.py
LbPlatformUtils/describe.py
LbPlatformUtils/inspect.py
LbPlatformUtils/platforms-list.json
lbplatformutils-4.5.1.dist-info/LICENSE
lbplatformutils-4.5.1.dist-info/METADATA
lbplatformutils-4.5.1.dist-info/WHEEL
lbplatformutils-4.5.1.dist-info/entry_points.txt
lbplatformutils-4.5.1.dist-info/RECORD
